beancount-3.2.0.dist-info/METADATA
beancount-3.2.0.dist-info/entry_points.txt
beancount-3.2.0.dist-info/WHEEL
beancount-3.2.0.dist-info/RECORD
beancount/api.py
beancount/__init__.py
beancount/loader_test.py
beancount/VERSION
beancount/py.typed
beancount/loader.py
beancount/utils/invariants.py
beancount/utils/file_utils_test.py
beancount/utils/pager.py
beancount/utils/encryption.py
beancount/utils/memo_test.py
beancount/utils/defdict.py
beancount/utils/file_utils.py
beancount/utils/test_utils_test.py
beancount/utils/defdict_test.py
beancount/utils/__init__.py
beancount/utils/table.py
beancount/utils/import_utils_test.py
beancount/utils/table_test.py
beancount/utils/bisect_key.py
beancount/utils/test_utils.py
beancount/utils/misc_utils.py
beancount/utils/memo.py
beancount/utils/pager_test.py
beancount/utils/invariants_test.py
beancount/utils/bisect_key_test.py
beancount/utils/encryption_test.py
beancount/utils/import_utils.py
beancount/utils/misc_utils_test.py
beancount/scripts/check.py
beancount/scripts/check_examples_test.py
beancount/scripts/doctor.py
beancount/scripts/directories.py
beancount/scripts/deps_test.py
beancount/scripts/format_test.py
beancount/scripts/__init__.py
beancount/scripts/directories_test.py
beancount/scripts/doctor_test.py
beancount/scripts/format.py
beancount/scripts/example_test.py
beancount/scripts/deps.py
beancount/scripts/example.py
beancount/scripts/check_test.py
beancount/projects/export_test.py
beancount/projects/__init__.py
beancount/projects/export.py
beancount/parser/version_test.py
beancount/parser/booking_method.py
beancount/parser/_parser.cpython-310-aarch64-linux-gnu.so
beancount/parser/grammar.y
beancount/parser/parser_test.py
beancount/parser/lexer.l
beancount/parser/tokens.h
beancount/parser/grammar.py
beancount/parser/hashsrc.py
beancount/parser/printer_test.py
beancount/parser/grammar_test.py
beancount/parser/context_test.py
beancount/parser/__init__.py
beancount/parser/version.py
beancount/parser/options.py
beancount/parser/decimal.h
beancount/parser/printer.py
beancount/parser/context.py
